dbpunctuator/__init__.py
dbpunctuator/data_process/__init__.py
dbpunctuator/data_process/data_cleanning.py
dbpunctuator/data_process/data_process.py
dbpunctuator/inference/__init__.py
dbpunctuator/inference/inference_interface.py
dbpunctuator/inference/inference_pipeline.py
dbpunctuator/training/__init__.py
dbpunctuator/training/evalute.py
dbpunctuator/training/general_ner_train.py
dbpunctuator/training/punctuation_data_process.py
dbpunctuator/training/train.py
dbpunctuator/utils/__init__.py
dbpunctuator/utils/additional_data_process.py
dbpunctuator/utils/constant.py
dbpunctuator/utils/model_test.py
dbpunctuator/utils/upload_model.py
dbpunctuator/utils/utils.py
distilbert_punctuator-0.3.0.dist-info/LICENSE
distilbert_punctuator-0.3.0.dist-info/METADATA
distilbert_punctuator-0.3.0.dist-info/WHEEL
distilbert_punctuator-0.3.0.dist-info/entry_points.txt
distilbert_punctuator-0.3.0.dist-info/top_level.txt
distilbert_punctuator-0.3.0.dist-info/RECORD
