Metadata-Version: 2.1
Name: distilbert-punctuator
Version: 0.3.0
Summary: A small seq2seq punctuator tool based on DistilBERT
Home-page: https://github.com/FerdinandZhong/punctuator
Author: Zhong Qishuai
Author-email: ferdinandzhong@gmail.com
License: UNKNOWN
Platform: UNKNOWN
Classifier: Programming Language :: Python :: 3 :: Only
Classifier: Programming Language :: Python :: 3.6
Classifier: Programming Language :: Python :: 3.7
Classifier: Programming Language :: Python :: 3.8
Classifier: Programming Language :: Python :: 3.9
Classifier: Topic :: Software Development :: Libraries :: Python Modules
Requires-Python: >3.6
Requires-Dist: torch (>=1.7.1)
Requires-Dist: typer (==0.3.2)
Requires-Dist: tqdm (>=4.61.2)
Requires-Dist: transformers (>=4.12.0)
Requires-Dist: pydantic (==1.8.2)
Requires-Dist: plane (>=0.2.0)
Provides-Extra: data_process
Requires-Dist: pandas (>=1.1.0) ; extra == 'data_process'
Provides-Extra: dev
Requires-Dist: pytest (>=6) ; extra == 'dev'
Requires-Dist: flake8 (>=3.8) ; extra == 'dev'
Requires-Dist: black (>=20.8b1) ; extra == 'dev'
Requires-Dist: isort (>=5.6) ; extra == 'dev'
Requires-Dist: autoflake (>=1.4) ; extra == 'dev'
Requires-Dist: pandas (>=1.1.0) ; extra == 'dev'
Requires-Dist: scikit-learn (>=0.23.2) ; extra == 'dev'
Provides-Extra: training
Requires-Dist: scikit-learn (>=0.23.2) ; extra == 'training'
Requires-Dist: tensorboard ; extra == 'training'
